<?xml version="1.0" encoding="utf-8" ?>
<dwsync>
<file name="1.jpg" server="i-d-e-e.it//" local="132760137447274191" remote="132963109800000000" Dst="2" />
<file name="10.jpg" server="i-d-e-e.it//" local="132760137529332897" remote="132963109800000000" Dst="2" />
<file name="100.jpg" server="i-d-e-e.it//" local="132743531048085428" remote="132963109800000000" Dst="2" />
<file name="11.jpg" server="i-d-e-e.it//" local="132760137550976387" remote="132963109800000000" Dst="2" />
<file name="12.jpg" server="i-d-e-e.it//" local="132760137551776136" remote="132963109800000000" Dst="2" />
<file name="13.jpg" server="i-d-e-e.it//" local="132760137572679371" remote="132963109800000000" Dst="2" />
<file name="15.jpg" server="i-d-e-e.it//" local="132760137593565201" remote="132963109800000000" Dst="2" />
<file name="14.jpg" server="i-d-e-e.it//" local="132760137573079242" remote="132963109800000000" Dst="2" />
<file name="16.jpg" server="i-d-e-e.it//" local="132760137596034407" remote="132963109800000000" Dst="2" />
<file name="18.jpg" server="i-d-e-e.it//" local="132743530265059175" remote="132963109800000000" Dst="2" />
<file name="17.jpg" server="i-d-e-e.it//" local="132743530265389073" remote="132963109800000000" Dst="2" />
<file name="2.jpg" server="i-d-e-e.it//" local="132760137446234527" remote="132963109800000000" Dst="2" />
<file name="19.jpg" server="i-d-e-e.it//" local="132743530283371454" remote="132963109800000000" Dst="2" />
<file name="20.jpg" server="i-d-e-e.it//" local="132743530281963888" remote="132963109800000000" Dst="2" />
<file name="21.jpg" server="i-d-e-e.it//" local="132743530304704779" remote="132963109800000000" Dst="2" />
<file name="22.jpg" server="i-d-e-e.it//" local="132743530305684477" remote="132963109800000000" Dst="2" />
<file name="23.jpg" server="i-d-e-e.it//" local="132743530327403984" remote="132963109800000000" Dst="2" />
<file name="24.jpg" server="i-d-e-e.it//" local="132743530327353998" remote="132963109800000000" Dst="2" />
<file name="25.jpg" server="i-d-e-e.it//" local="132743530343988792" remote="132963109800000000" Dst="2" />
<file name="26.jpg" server="i-d-e-e.it//" local="132743530343928812" remote="132963109800000000" Dst="2" />
<file name="27.jpg" server="i-d-e-e.it//" local="132743530365032206" remote="132963109800000000" Dst="2" />
<file name="28.jpg" server="i-d-e-e.it//" local="132743530365701999" remote="132963109800000000" Dst="2" />
<file name="3.jpg" server="i-d-e-e.it//" local="132760137467959795" remote="132963109800000000" Dst="2" />
<file name="29.jpg" server="i-d-e-e.it//" local="132743530391134252" remote="132963109800000000" Dst="2" />
<file name="30.jpg" server="i-d-e-e.it//" local="132743530383676379" remote="132963109800000000" Dst="2" />
<file name="32.jpg" server="i-d-e-e.it//" local="132743530409548772" remote="132963109800000000" Dst="2" />
<file name="31.jpg" server="i-d-e-e.it//" local="132743530409698723" remote="132963109800000000" Dst="2" />
<file name="33.jpg" server="i-d-e-e.it//" local="132743530433061613" remote="132963109800000000" Dst="2" />
<file name="34.jpg" server="i-d-e-e.it//" local="132743530433901352" remote="132963109800000000" Dst="2" />
<file name="35.jpg" server="i-d-e-e.it//" local="132743530455944448" remote="132963109800000000" Dst="2" />
<file name="36.jpg" server="i-d-e-e.it//" local="132743530455384625" remote="132963109800000000" Dst="2" />
<file name="37.jpg" server="i-d-e-e.it//" local="132743530476887899" remote="132963109800000000" Dst="2" />
<file name="38.jpg" server="i-d-e-e.it//" local="132743530471939448" remote="132963109800000000" Dst="2" />
<file name="39.jpg" server="i-d-e-e.it//" local="132743530494382432" remote="132963109800000000" Dst="2" />
<file name="4.jpg" server="i-d-e-e.it//" local="132760137463438960" remote="132963109800000000" Dst="2" />
<file name="40.jpg" server="i-d-e-e.it//" local="132743530493312764" remote="132963109800000000" Dst="2" />
<file name="41.jpg" server="i-d-e-e.it//" local="132743530515595791" remote="132963109800000000" Dst="2" />
<file name="42.jpg" server="i-d-e-e.it//" local="132743530515495821" remote="132963109800000000" Dst="2" />
<file name="43.jpg" server="i-d-e-e.it//" local="132743530533670132" remote="132963109800000000" Dst="2" />
<file name="44.jpg" server="i-d-e-e.it//" local="132743530533620144" remote="132963109800000000" Dst="2" />
<file name="45.jpg" server="i-d-e-e.it//" local="132743530551614552" remote="132963109800000000" Dst="2" />
<file name="46.jpg" server="i-d-e-e.it//" local="132743530550474902" remote="132963109800000000" Dst="2" />
<file name="47.jpg" server="i-d-e-e.it//" local="132743530572433081" remote="132963109800000000" Dst="2" />
<file name="48.jpg" server="i-d-e-e.it//" local="132743530572423085" remote="132963109800000000" Dst="2" />
<file name="49.jpg" server="i-d-e-e.it//" local="132743530594026319" remote="132963109800000000" Dst="2" />
<file name="5.jpg" server="i-d-e-e.it//" local="132760137485614075" remote="132963109800000000" Dst="2" />
<file name="50.jpg" server="i-d-e-e.it//" local="132743530594666126" remote="132963109800000000" Dst="2" />
<file name="51.jpg" server="i-d-e-e.it//" local="132743530617828872" remote="132963109800000000" Dst="2" />
<file name="52.jpg" server="i-d-e-e.it//" local="132743530616149399" remote="132963109800000000" Dst="2" />
<file name="53.jpg" server="i-d-e-e.it//" local="132743530637792637" remote="132963109800000000" Dst="2" />
<file name="55.jpg" server="i-d-e-e.it//" local="132743530657266536" remote="132963109800000000" Dst="2" />
<file name="54.jpg" server="i-d-e-e.it//" local="132743530635923211" remote="132963109800000000" Dst="2" />
<file name="56.jpg" server="i-d-e-e.it//" local="132743530661395485" remote="132963109800000000" Dst="2" />
<file name="57.jpg" server="i-d-e-e.it//" local="132743530682668831" remote="132963109800000000" Dst="2" />
<file name="58.jpg" server="i-d-e-e.it//" local="132743530686997477" remote="132963109800000000" Dst="2" />
<file name="59.jpg" server="i-d-e-e.it//" local="132743530705631636" remote="132963109800000000" Dst="2" />
<file name="6.jpg" server="i-d-e-e.it//" local="132760137489542939" remote="132963109800000000" Dst="2" />
<file name="60.jpg" server="i-d-e-e.it//" local="132743530704342042" remote="132963109800000000" Dst="2" />
<file name="61.jpg" server="i-d-e-e.it//" local="132743530864527179" remote="132963109800000000" Dst="2" />
<file name="62.jpg" server="i-d-e-e.it//" local="132743530865326931" remote="132963109800000000" Dst="2" />
<file name="63.jpg" server="i-d-e-e.it//" local="132743530864187289" remote="132963109800000000" Dst="2" />
<file name="64.jpg" server="i-d-e-e.it//" local="132743530872284947" remote="132963109800000000" Dst="2" />
<file name="65.jpg" server="i-d-e-e.it//" local="132743530886510495" remote="132963109800000000" Dst="2" />
<file name="66.jpg" server="i-d-e-e.it//" local="132743530881552050" remote="132963109800000000" Dst="2" />
<file name="67.jpg" server="i-d-e-e.it//" local="132743530881442082" remote="132963109800000000" Dst="2" />
<file name="68.jpg" server="i-d-e-e.it//" local="132743530890719181" remote="132963109800000000" Dst="2" />
<file name="69.jpg" server="i-d-e-e.it//" local="132743530903635139" remote="132963109800000000" Dst="2" />
<file name="7.jpg" server="i-d-e-e.it//" local="132760137507659912" remote="132963109800000000" Dst="2" />
<file name="70.jpg" server="i-d-e-e.it//" local="132743530904294926" remote="132963109800000000" Dst="2" />
<file name="71.jpg" server="i-d-e-e.it//" local="132743530910633074" remote="132963109800000000" Dst="2" />
<file name="72.jpg" server="i-d-e-e.it//" local="132743530908433756" remote="132963109800000000" Dst="2" />
<file name="73.jpg" server="i-d-e-e.it//" local="132743530927373526" remote="132963109800000000" Dst="2" />
<file name="74.jpg" server="i-d-e-e.it//" local="132743530927063623" remote="132963109800000000" Dst="2" />
<file name="75.jpg" server="i-d-e-e.it//" local="132743530926313858" remote="132963109800000000" Dst="2" />
<file name="76.jpg" server="i-d-e-e.it//" local="132743530929672833" remote="132963109800000000" Dst="2" />
<file name="78.jpg" server="i-d-e-e.it//" local="132743530945008003" remote="132963109800000000" Dst="2" />
<file name="77.jpg" server="i-d-e-e.it//" local="132743530946457566" remote="132963109800000000" Dst="2" />
<file name="79.jpg" server="i-d-e-e.it//" local="132743530945357899" remote="132963109800000000" Dst="2" />
<file name="8.jpg" server="i-d-e-e.it//" local="132760137511338726" remote="132963109800000000" Dst="2" />
<file name="80.jpg" server="i-d-e-e.it//" local="132743530947757146" remote="132963109800000000" Dst="2" />
<file name="81.jpg" server="i-d-e-e.it//" local="132743530966781215" remote="132963109800000000" Dst="2" />
<file name="82.jpg" server="i-d-e-e.it//" local="132743530962582507" remote="132963109800000000" Dst="2" />
<file name="84.jpg" server="i-d-e-e.it//" local="132743530964721840" remote="132963109800000000" Dst="2" />
<file name="83.jpg" server="i-d-e-e.it//" local="132743530965751514" remote="132963109800000000" Dst="2" />
<file name="85.jpg" server="i-d-e-e.it//" local="132743530984325705" remote="132963109800000000" Dst="2" />
<file name="86.jpg" server="i-d-e-e.it//" local="132743530981716520" remote="132963109800000000" Dst="2" />
<file name="87.jpg" server="i-d-e-e.it//" local="132743530984485658" remote="132963109800000000" Dst="2" />
<file name="88.jpg" server="i-d-e-e.it//" local="132743530983326018" remote="132963109800000000" Dst="2" />
<file name="89.jpg" server="i-d-e-e.it//" local="132743531007418517" remote="132963109800000000" Dst="2" />
<file name="90.jpg" server="i-d-e-e.it//" local="132743531009107956" remote="132963109800000000" Dst="2" />
<file name="9.jpg" server="i-d-e-e.it//" local="132760137530632477" remote="132963109800000000" Dst="2" />
<file name="91.jpg" server="i-d-e-e.it//" local="132743531006268861" remote="132963109800000000" Dst="2" />
<file name="92.jpg" server="i-d-e-e.it//" local="132743531004909267" remote="132963109800000000" Dst="2" />
<file name="93.jpg" server="i-d-e-e.it//" local="132743531028201658" remote="132963109800000000" Dst="2" />
<file name="94.jpg" server="i-d-e-e.it//" local="132743531029261318" remote="132963109800000000" Dst="2" />
<file name="95.jpg" server="i-d-e-e.it//" local="132743531024822709" remote="132963109800000000" Dst="2" />
<file name="96.jpg" server="i-d-e-e.it//" local="132743531026482189" remote="132963109800000000" Dst="2" />
<file name="99.jpg" server="i-d-e-e.it//" local="132743531043236944" remote="132963109800000000" Dst="2" />
<file name="97.jpg" server="i-d-e-e.it//" local="132743531048315360" remote="132963109800000000" Dst="2" />
<file name="98.jpg" server="i-d-e-e.it//" local="132743531044436573" remote="132963109800000000" Dst="2" />
</dwsync>