<?xml version="1.0" encoding="utf-8" ?>
<dwsync>
<file name="1.jpg" server="i-d-e-e.it//" local="132763311450644508" remote="132925162200000000" Dst="1" />
<file name="10.jpg" server="i-d-e-e.it//" local="132760159340000000" remote="132925162200000000" Dst="1" />
<file name="100.jpg" server="i-d-e-e.it//" local="132744330623408309" remote="132925162200000000" Dst="1" />
<file name="11.jpg" server="i-d-e-e.it//" local="132760159360000000" remote="132925162200000000" Dst="1" />
<file name="12.jpg" server="i-d-e-e.it//" local="132760159340000000" remote="132925162200000000" Dst="1" />
<file name="13.jpg" server="i-d-e-e.it//" local="132760159360000000" remote="132925162200000000" Dst="1" />
<file name="14.jpg" server="i-d-e-e.it//" local="132760159360000000" remote="132925162200000000" Dst="1" />
<file name="15.jpg" server="i-d-e-e.it//" local="132744330378152026" remote="132925162200000000" Dst="1" />
<file name="16.jpg" server="i-d-e-e.it//" local="132744330379931490" remote="132925162200000000" Dst="1" />
<file name="17.jpg" server="i-d-e-e.it//" local="132744330381930883" remote="132925162200000000" Dst="1" />
<file name="18.jpg" server="i-d-e-e.it//" local="132744330416130607" remote="132925162200000000" Dst="1" />
<file name="19.jpg" server="i-d-e-e.it//" local="132744330415480799" remote="132925162200000000" Dst="1" />
<file name="2.jpg" server="i-d-e-e.it//" local="132760159320000000" remote="132925162200000000" Dst="1" />
<file name="20.jpg" server="i-d-e-e.it//" local="132744330385799722" remote="132925162200000000" Dst="1" />
<file name="21.jpg" server="i-d-e-e.it//" local="132744330389458622" remote="132925162200000000" Dst="1" />
<file name="22.jpg" server="i-d-e-e.it//" local="132744330393577383" remote="132925162200000000" Dst="1" />
<file name="24.jpg" server="i-d-e-e.it//" local="132744330396946373" remote="132925162200000000" Dst="1" />
<file name="23.jpg" server="i-d-e-e.it//" local="132744330427987046" remote="132925162200000000" Dst="1" />
<file name="25.jpg" server="i-d-e-e.it//" local="132744330402704642" remote="132925162200000000" Dst="1" />
<file name="26.jpg" server="i-d-e-e.it//" local="132744330406573477" remote="132925162200000000" Dst="1" />
<file name="27.jpg" server="i-d-e-e.it//" local="132744330410242382" remote="132925162200000000" Dst="1" />
<file name="28.jpg" server="i-d-e-e.it//" local="132744330414201193" remote="132925162200000000" Dst="1" />
<file name="29.jpg" server="i-d-e-e.it//" local="132744330417850091" remote="132925162200000000" Dst="1" />
<file name="3.jpg" server="i-d-e-e.it//" local="132763311463560805" remote="132925162200000000" Dst="1" />
<file name="30.jpg" server="i-d-e-e.it//" local="132744330419819499" remote="132925162200000000" Dst="1" />
<file name="32.jpg" server="i-d-e-e.it//" local="132744330421798901" remote="132925162200000000" Dst="1" />
<file name="31.jpg" server="i-d-e-e.it//" local="132744330453989227" remote="132925162200000000" Dst="1" />
<file name="33.jpg" server="i-d-e-e.it//" local="132744330425677737" remote="132925162200000000" Dst="1" />
<file name="34.jpg" server="i-d-e-e.it//" local="132744330425777706" remote="132925162200000000" Dst="1" />
<file name="35.jpg" server="i-d-e-e.it//" local="132744330429566566" remote="132925162200000000" Dst="1" />
<file name="36.jpg" server="i-d-e-e.it//" local="132744330430136399" remote="132925162200000000" Dst="1" />
<file name="38.jpg" server="i-d-e-e.it//" local="132744330433395417" remote="132925162200000000" Dst="1" />
<file name="37.jpg" server="i-d-e-e.it//" local="132744330464745992" remote="132925162200000000" Dst="1" />
<file name="39.jpg" server="i-d-e-e.it//" local="132744330441872868" remote="132925162200000000" Dst="1" />
<file name="40.jpg" server="i-d-e-e.it//" local="132744330439103703" remote="132925162200000000" Dst="1" />
<file name="4.jpg" server="i-d-e-e.it//" local="132760159340000000" remote="132925162200000000" Dst="1" />
<file name="41.jpg" server="i-d-e-e.it//" local="132744330442872569" remote="132925162200000000" Dst="1" />
<file name="43.jpg" server="i-d-e-e.it//" local="132744330446801387" remote="132925162200000000" Dst="1" />
<file name="42.jpg" server="i-d-e-e.it//" local="132744330478821761" remote="132925162200000000" Dst="1" />
<file name="44.jpg" server="i-d-e-e.it//" local="132744330450510276" remote="132925162200000000" Dst="1" />
<file name="45.jpg" server="i-d-e-e.it//" local="132744330453619342" remote="132925162200000000" Dst="1" />
<file name="46.jpg" server="i-d-e-e.it//" local="132744330459677520" remote="132925162200000000" Dst="1" />
<file name="48.jpg" server="i-d-e-e.it//" local="132744330463286432" remote="132925162200000000" Dst="1" />
<file name="47.jpg" server="i-d-e-e.it//" local="132744330490728187" remote="132925162200000000" Dst="1" />
<file name="49.jpg" server="i-d-e-e.it//" local="132744330466875358" remote="132925162200000000" Dst="1" />
<file name="50.jpg" server="i-d-e-e.it//" local="132744330468264937" remote="132925162200000000" Dst="1" />
<file name="5.jpg" server="i-d-e-e.it//" local="132760159360000000" remote="132925162200000000" Dst="1" />
<file name="51.jpg" server="i-d-e-e.it//" local="132744330472853566" remote="132925162200000000" Dst="1" />
<file name="52.jpg" server="i-d-e-e.it//" local="132744330472263734" remote="132925162200000000" Dst="1" />
<file name="54.jpg" server="i-d-e-e.it//" local="132744330476762384" remote="132925162200000000" Dst="1" />
<file name="53.jpg" server="i-d-e-e.it//" local="132744330509222631" remote="132925162200000000" Dst="1" />
<file name="55.jpg" server="i-d-e-e.it//" local="132744330482380692" remote="132925162200000000" Dst="1" />
<file name="56.jpg" server="i-d-e-e.it//" local="132744330482710598" remote="132925162200000000" Dst="1" />
<file name="57.jpg" server="i-d-e-e.it//" local="132744330494337097" remote="132925162200000000" Dst="1" />
<file name="58.jpg" server="i-d-e-e.it//" local="132744330488678802" remote="132925162200000000" Dst="1" />
<file name="59.jpg" server="i-d-e-e.it//" local="132744330492447667" remote="132925162200000000" Dst="1" />
<file name="6.jpg" server="i-d-e-e.it//" local="132760159320000000" remote="132925162200000000" Dst="1" />
<file name="60.jpg" server="i-d-e-e.it//" local="132744330495016898" remote="132925162200000000" Dst="1" />
<file name="61.jpg" server="i-d-e-e.it//" local="132744330528366873" remote="132925162200000000" Dst="1" />
<file name="62.jpg" server="i-d-e-e.it//" local="132744330504703987" remote="132925162200000000" Dst="1" />
<file name="63.jpg" server="i-d-e-e.it//" local="132744330501035088" remote="132925162200000000" Dst="1" />
<file name="64.jpg" server="i-d-e-e.it//" local="132744330505273832" remote="132925162200000000" Dst="1" />
<file name="66.jpg" server="i-d-e-e.it//" local="132744330509142652" remote="132925162200000000" Dst="1" />
<file name="65.jpg" server="i-d-e-e.it//" local="132744330539183623" remote="132925162200000000" Dst="1" />
<file name="67.jpg" server="i-d-e-e.it//" local="132744330515260815" remote="132925162200000000" Dst="1" />
<file name="68.jpg" server="i-d-e-e.it//" local="132744330512831542" remote="132925162200000000" Dst="1" />
<file name="69.jpg" server="i-d-e-e.it//" local="132744330548870709" remote="132925162200000000" Dst="1" />
<file name="70.jpg" server="i-d-e-e.it//" local="132744330520919109" remote="132925162200000000" Dst="1" />
<file name="7.jpg" server="i-d-e-e.it//" local="132760159360000000" remote="132925162200000000" Dst="1" />
<file name="71.jpg" server="i-d-e-e.it//" local="132744330524647992" remote="132925162200000000" Dst="1" />
<file name="72.jpg" server="i-d-e-e.it//" local="132744330535514728" remote="132925162200000000" Dst="1" />
<file name="74.jpg" server="i-d-e-e.it//" local="132744330539303587" remote="132925162200000000" Dst="1" />
<file name="73.jpg" server="i-d-e-e.it//" local="132744330538063960" remote="132925162200000000" Dst="1" />
<file name="75.jpg" server="i-d-e-e.it//" local="132744330541762847" remote="132925162200000000" Dst="1" />
<file name="76.jpg" server="i-d-e-e.it//" local="132744330543172422" remote="132925162200000000" Dst="1" />
<file name="77.jpg" server="i-d-e-e.it//" local="132744330573943175" remote="132925162200000000" Dst="1" />
<file name="78.jpg" server="i-d-e-e.it//" local="132744330545291788" remote="132925162200000000" Dst="1" />
<file name="79.jpg" server="i-d-e-e.it//" local="132744330564066143" remote="132925162200000000" Dst="1" />
<file name="8.jpg" server="i-d-e-e.it//" local="132760159320000000" remote="132925162200000000" Dst="1" />
<file name="80.jpg" server="i-d-e-e.it//" local="132744330559267586" remote="132925162200000000" Dst="1" />
<file name="81.jpg" server="i-d-e-e.it//" local="132744330563486319" remote="132925162200000000" Dst="1" />
<file name="82.jpg" server="i-d-e-e.it//" local="132744330570544197" remote="132925162200000000" Dst="1" />
<file name="83.jpg" server="i-d-e-e.it//" local="132744330576982262" remote="132925162200000000" Dst="1" />
<file name="84.jpg" server="i-d-e-e.it//" local="132744330575682654" remote="132925162200000000" Dst="1" />
<file name="85.jpg" server="i-d-e-e.it//" local="132744330583380339" remote="132925162200000000" Dst="1" />
<file name="86.jpg" server="i-d-e-e.it//" local="132744330624437998" remote="132925162200000000" Dst="1" />
<file name="87.jpg" server="i-d-e-e.it//" local="132744330590628160" remote="132925162200000000" Dst="1" />
<file name="89.jpg" server="i-d-e-e.it//" local="132744330587689045" remote="132925162200000000" Dst="1" />
<file name="88.jpg" server="i-d-e-e.it//" local="132744330590638162" remote="132925162200000000" Dst="1" />
<file name="9.jpg" server="i-d-e-e.it//" local="132760159320000000" remote="132925162200000000" Dst="1" />
<file name="90.jpg" server="i-d-e-e.it//" local="132744330591347945" remote="132925162200000000" Dst="1" />
<file name="91.jpg" server="i-d-e-e.it//" local="132744330594896876" remote="132925162200000000" Dst="1" />
<file name="92.jpg" server="i-d-e-e.it//" local="132744330598835691" remote="132925162200000000" Dst="1" />
<file name="93.jpg" server="i-d-e-e.it//" local="132744330595316752" remote="132925162200000000" Dst="1" />
<file name="94.jpg" server="i-d-e-e.it//" local="132744330599145599" remote="132925162200000000" Dst="1" />
<file name="95.jpg" server="i-d-e-e.it//" local="132744330608892669" remote="132925162200000000" Dst="1" />
<file name="96.jpg" server="i-d-e-e.it//" local="132744330612901466" remote="132925162200000000" Dst="1" />
<file name="97.jpg" server="i-d-e-e.it//" local="132744330634305034" remote="132925162200000000" Dst="1" />
<file name="98.jpg" server="i-d-e-e.it//" local="132744330612811491" remote="132925162200000000" Dst="1" />
<file name="99.jpg" server="i-d-e-e.it//" local="132744330621458896" remote="132925162200000000" Dst="1" />
</dwsync>